{
  "status": "success",
  "owner": "MD ANAMUL HOQUE",
  "telegram": "https://t.me/ireentv",
  "website": "https://anamul.pages.dev",
  "developer": "IreenTechnology",
  "version": "1.0",
  "name": "tapmad_bd",
  "channels_amount": 3,
  "Last_update": "2026-07-20 10:10:19 AM",
  "channels": [
    {
      "name": "MI London vs Sunrisers Leeds - Women",
      "logo": "https://d34080pnh6e62j.cloudfront.net/images/channels/ChannelFeaturedAppthumb/1784537072540x302women.jpg",
      "url": "https://upcoming-match-no-stream.m3u8",
      "group": "General",
      "url_raw": "https://upcoming-match-no-stream.m3u8",
      "status": "Upcoming"
    },
    {
      "name": "MI London vs Sunrisers Leeds",
      "logo": "https://d34080pnh6e62j.cloudfront.net/images/channels/ChannelFeaturedAppthumb/1784538587540x302men.jpg",
      "url": "https://upcoming-match-no-stream.m3u8",
      "group": "General",
      "url_raw": "https://upcoming-match-no-stream.m3u8",
      "status": "Upcoming"
    },
    {
      "name": "West Indies vs New Zealand",
      "logo": "https://d34080pnh6e62j.cloudfront.net/images/channels/ChannelFeaturedAppthumb/1784526285540x302.jpg",
      "url": "https://upcoming-match-no-stream.m3u8",
      "group": "General",
      "url_raw": "https://upcoming-match-no-stream.m3u8",
      "status": "Upcoming"
    }
  ]
}